pyfizi/__init__.py
pyfizi/alleles.py
pyfizi/annot.py
pyfizi/gwas.py
pyfizi/impute.py
pyfizi/infer.py
pyfizi/io.py
pyfizi/ref.py
pyfizi/taus.py
pyfizi-0.7.2.data/scripts/fizi
pyfizi-0.7.2.dist-info/LICENSE
pyfizi-0.7.2.dist-info/METADATA
pyfizi-0.7.2.dist-info/WHEEL
pyfizi-0.7.2.dist-info/top_level.txt
pyfizi-0.7.2.dist-info/RECORD
