Metadata-Version: 2.1
Name: pyfizi
Version: 0.7.2
Summary: Impute GWAS summary statistics using reference genotype data
Home-page: https://github.com/bogdanlab/fizi
Author: Nicholas Mancuso, Megan Roytman
Author-email: nicholas.mancuso@med.usc.edu
License: UNKNOWN
Platform: UNKNOWN
Classifier: Programming Language :: Python :: 3
Classifier: License :: OSI Approved :: GNU General Public License v3 or later (GPLv3+)
Classifier: Operating System :: OS Independent
Requires-Python: >=3
Requires-Dist: numpy (>=1.14.5)
Requires-Dist: scipy (>=1.2.0)
Requires-Dist: pandas (>=1.2.0)
Requires-Dist: pandas-plink
